hsxworkflow/Config.py
hsxworkflow/WorkFlowMain.py
hsxworkflow/__init__.py
hsxworkflow/Code/StepAction.py
hsxworkflow/Code/StepActionUtils.py
hsxworkflow/Code/WorkFlowHandler.py
hsxworkflow/Code/WorkRegister.py
hsxworkflow/Code/__init__.py
hsxworkflow/DP/DPClient.py
hsxworkflow/DP/__init__.py
hsxworkflow/Utils/RecordHandler.py
hsxworkflow/Utils/__init__.py
hsxworkflow/Utils/database.py
hsxworkflow/Utils/handler.py
hsxworkflow/Utils/logger.py
hsxworkflow/Utils/redis_handler.py
hsxworkflow/Web/__init__.py
hsxworkflow/Web/base_handler.py
hsxworkflow/Web/flask_main.py
hsxworkflow/Web/api/__init__.py
hsxworkflow/Web/api/work_flow_api.py
hsxworkflow/Web/assets/HomePage-7yTsW4Sp.js
hsxworkflow/Web/assets/HomePage-djHPG_zX.css
hsxworkflow/Web/assets/WorkDetails-DsFYA1cM.css
hsxworkflow/Web/assets/WorkDetails-PZGIvujB.js
hsxworkflow/Web/assets/_plugin-vue_export-helper-CVQjx7MO.js
hsxworkflow/Web/assets/_plugin-vue_export-helper-Ctohz2Sb.css
hsxworkflow/Web/assets/index-5xaF469R.css
hsxworkflow/Web/assets/index-DU1D7W6J.js
hsxworkflow/Web/assets/logo-BIwJ2Vs1.png
hsxworkflow/Web/page/__init__.py
hsxworkflow/Web/page/index.py
hsxworkflow/Web/socket/__init__.py
hsxworkflow/Web/socket/workflow_socket.py
hsxworkflow/Web/templates/favicon.ico
hsxworkflow/Web/templates/index.html
hsxworkflow/Web/templates/logo.png
hsxworkflow-0.1.1.dist-info/METADATA
hsxworkflow-0.1.1.dist-info/WHEEL
hsxworkflow-0.1.1.dist-info/entry_points.txt
hsxworkflow-0.1.1.dist-info/licenses/LICENSE
hsxworkflow-0.1.1.dist-info/RECORD
