Metadata-Version: 2.4
Name: hsxworkflow
Version: 0.1.1
Summary: 工作流软件
License-File: LICENSE
Requires-Python: >=3.8
Requires-Dist: aiomysql==0.2.0
Requires-Dist: async-timeout==5.0.1
Requires-Dist: blinker==1.8.2
Requires-Dist: certifi==2025.1.31
Requires-Dist: charset-normalizer==3.4.1
Requires-Dist: click==8.1.8
Requires-Dist: colorama==0.4.6
Requires-Dist: cssselect==1.2.0
Requires-Dist: datarecorder==3.6.2
Requires-Dist: dill==0.4.0
Requires-Dist: downloadkit==2.0.7
Requires-Dist: drissionpage==4.1.0.18
Requires-Dist: et-xmlfile==2.0.0
Requires-Dist: filelock==3.16.1
Requires-Dist: flask-cors==5.0.0
Requires-Dist: flask-socketio>=5.5.1
Requires-Dist: flask==3.0.3
Requires-Dist: idna==3.10
Requires-Dist: importlib-metadata==8.5.0
Requires-Dist: itsdangerous==2.2.0
Requires-Dist: jinja2==3.1.6
Requires-Dist: lxml==5.3.2
Requires-Dist: markupsafe==2.1.5
Requires-Dist: openpyxl==3.1.5
Requires-Dist: pip==23.0.1
Requires-Dist: psutil==7.0.0
Requires-Dist: pymysql==1.1.1
Requires-Dist: redis==5.2.1
Requires-Dist: requests-file==2.1.0
Requires-Dist: requests==2.32.3
Requires-Dist: setuptools==56.0.0
Requires-Dist: tldextract==5.1.2
Requires-Dist: urllib3==2.2.3
Requires-Dist: websocket-client==1.8.0
Requires-Dist: werkzeug==3.0.6
Requires-Dist: zipp==3.20.2
